mdes/__init__.py
mdes/cmd.py
mdes/event.py
mdes/event_queue.py
mdes/event_types.py
mdes/process.py
mdes/process_generator.py
mdes/process_queue.py
mdes/processor.py
mdes/queue.py
mdes/simulator.py
mdes-0.1.1.dist-info/METADATA
mdes-0.1.1.dist-info/RECORD
mdes-0.1.1.dist-info/WHEEL
mdes-0.1.1.dist-info/entry_points.txt
mdes-0.1.1.dist-info/top_level.txt
