Metadata-Version: 2.1
Name: mdes
Version: 0.1.1
Summary: Modular Discrete Event Simulator
Home-page: https://github.com/panagiks/MDES
Author: Kolokotronis Panagiotis
Author-email: UNKNOWN
License: MIT
Platform: UNKNOWN
Classifier: License :: OSI Approved :: MIT License
Classifier: Development Status :: 4 - Beta
Classifier: Environment :: Console
Classifier: Intended Audience :: Information Technology
Classifier: Intended Audience :: Science/Research
Classifier: Natural Language :: English
Classifier: Programming Language :: Python
Classifier: Programming Language :: Python :: 3
Classifier: Topic :: Scientific/Engineering
Requires-Dist: click
